py_twelvelabs/__init__.py
py_twelvelabs/client.py
py_twelvelabs/exceptions.py
py_twelvelabs/models/__init__.py
py_twelvelabs/models/index.py
py_twelvelabs/models/task.py
py_twelvelabs/resources/__init__.py
py_twelvelabs/resources/index.py
py_twelvelabs/resources/search.py
py_twelvelabs/resources/task.py
py_twelvelabs/settings.py
py_twelvelabs/utilities/__init__.py
py_twelvelabs/utilities/logger.py
py_twelvelabs-0.1.0.dist-info/LICENSE
py_twelvelabs-0.1.0.dist-info/METADATA
py_twelvelabs-0.1.0.dist-info/WHEEL
py_twelvelabs-0.1.0.dist-info/RECORD
