Metadata-Version: 2.1
Name: py-twelvelabs
Version: 0.1.0
Summary: 
Author: Minura Punchihewa
Author-email: minurapunchihewa17@gmail.com
Requires-Python: >=3.8
Classifier: Programming Language :: Python :: 3
Classifier: Programming Language :: Python :: 3.8
Classifier: Programming Language :: Python :: 3.9
Classifier: Programming Language :: Python :: 3.10
Classifier: Programming Language :: Python :: 3.11
Requires-Dist: pydantic (>=2.5.2,<3.0.0)
Requires-Dist: pydantic-settings (>=2.1.0,<3.0.0)
Requires-Dist: requests (>=2.31.0,<3.0.0)
Requires-Dist: requests-toolbelt (>=1.0.0,<2.0.0)
